{
  "_meta": {
    "sources": [
      "../common/core",
      "../common/storage",
      "../common/workflow",
      "../common/project",
      "../common/hr",
      "../common/models",
      "../common/product",
      "../common/member"
    ]
  },
  "User": {
    "dataSource": "local",
    "public": true
  },
  "AccessToken": {
    "dataSource": "local",
    "public": true
  },
  "Role": {
    "dataSource": "local",
    "public": true
  },
  "RoleMapping": {
    "dataSource": "local",
    "public": true
  },
  "ACL": {
    "dataSource": "local",
    "public": true
  },
  "Email": {
    "dataSource": "mailDS"
  },
  "Item": {
    "dataSource": "local",
    "public": true
  },
  "List": {
    "dataSource": "local",
    "public": true
  },
  "ColumnDef": {
    "dataSource": "local",
    "public": true
  },
  "View": {
    "dataSource": "local",
    "public": true
  },
  "Attachment": {
    "dataSource": "attachment",
    "public": true
  },
  "ModerationComment": {
    "dataSource": "local",
    "public": true
  },
  "Task": {
    "dataSource": "local",
    "public": true
  },
  "WorkflowTemplate": {
    "dataSource": "local",
    "public": true
  },
  "WorkflowAssociation": {
    "dataSource": "local",
    "public": true
  },
  "WorkflowInstance": {
    "dataSource": "local",
    "public": true
  },
  "WorkflowTask": {
    "dataSource": "local",
    "public": true
  },
  "WorkflowLog": {
    "dataSource": "local",
    "public": true
  },
  "Post": {
    "dataSource": "local",
    "public": true
  },
  "Person": {
    "dataSource": "local",
    "public": true
  },
  "Alert": {
    "dataSource": "local",
    "public": true
  },
  "DocumentLibrary": {
    "dataSource": "document",
    "public": true
  },
  "General": {
    "dataSource": "local",
    "public": true
  },
  "TravelRequest": {
    "dataSource": "local",
    "public": true
  },
  "ExpensesClaimRequest": {
    "dataSource": "local",
    "public": true
  }
}
